{
  "dialog": {
        "dialogText": "Upon his death bed your grandfather holds your hand and explains \"You see this house, when your father was alive he wanted you to live peacefully without worrying about money so he had begun to build this place for you and your mother, unfortunately they both died in that horrible accident and he couldn't finish the task. I love you, since the first time I saw you when you were little and all these years taking care of you have been wonderful, but I am very old and my time is counted. My dear I want you to have this house, and live a happy life like your father and mother wanted for you.\"",
        "choice": {
          "choice1Text": "Go towards the town",
          "choice1Link": "/dialogs-data/dialog1",
          "choice2Text": "Go towards the farm",
          "choice2Link": "/dialogs-data/dialog2",
          "choice3Text": "Go towards the forest",
          "choice3Link": "/dialogs-data/dialog3"
        }
    },

  "dialog1": {
        "dialogText": "dialog 1 text",
        "choice": {
          "choice1Text": "Cloud City Bridge",
          "choice1Link": "Don't forget lightsaber",
          "choice2Text": "text",
          "choice2Link": "link",
          "choice3Text": "text",
          "choice3Link": "link"
        }
    },

  "dialog2": {
        "dialogText": "dialog 2 text",
        "choice": {
          "choice1Text": "Cloud City Bridge",
          "choice1Link": "Don't forget lightsaber",
          "choice2Text": "text",
          "choice2Link": "link",
          "choice3Text": "text",
          "choice3Link": "link"
        }
    },

  "dialog3": {
        "dialogText": "dialog 1 text",
        "choice": {
          "choice1Text": "Cloud City Bridge",
          "choice1Link": "Don't forget lightsaber",
          "choice2Text": "text",
          "choice2Link": "link",
          "choice3Text": "text",
          "choice3Link": "link"
        }
    },

  "dialog11": {
        "dialogText": "dialog 1 text",
        "choice": {
          "choice1Text": "Cloud City Bridge",
          "choice1Link": "Don't forget lightsaber",
          "choice2Text": "text",
          "choice2Link": "link",
          "choice3Text": "text",
          "choice3Link": "link"
        }
    },

  "dialog12": {
        "dialogText": "dialog 1 text",
        "choice": {
          "choice1Text": "Cloud City Bridge",
          "choice1Link": "Don't forget lightsaber",
          "choice2Text": "text",
          "choice2Link": "link",
          "choice3Text": "text",
          "choice3Link": "link"
        }
    },
  "dialog13": {
        "dialogText": "dialog 1 text",
        "choice": {
          "choice1Text": "Cloud City Bridge",
          "choice1Link": "Don't forget lightsaber",
          "choice2Text": "text",
          "choice2Link": "link",
          "choice3Text": "text",
          "choice3Link": "link"
        }
    },

  "dialog21": {
        "dialogText": "dialog 1 text",
        "choice": {
          "choice1Text": "Cloud City Bridge",
          "choice1Link": "Don't forget lightsaber",
          "choice2Text": "text",
          "choice2Link": "link",
          "choice3Text": "text",
          "choice3Link": "link"
        }
    },

  "dialog22": {
        "dialogText": "dialog 1 text",
        "choice": {
          "choice1Text": "Cloud City Bridge",
          "choice1Link": "Don't forget lightsaber",
          "choice2Text": "text",
          "choice2Link": "link",
          "choice3Text": "text",
          "choice3Link": "link"
        }
    },

  "dialog23": {
        "dialogText": "dialog 1 text",
        "choice": {
          "choice1Text": "Cloud City Bridge",
          "choice1Link": "Don't forget lightsaber",
          "choice2Text": "text",
          "choice2Link": "link",
          "choice3Text": "text",
          "choice3Link": "link"
        }
    },

  "dialog31": {
        "dialogText": "dialog 1 text",
        "choice": {
          "choice1Text": "Cloud City Bridge",
          "choice1Link": "Don't forget lightsaber",
          "choice2Text": "text",
          "choice2Link": "link",
          "choice3Text": "text",
          "choice3Link": "link"
        }
    },

  "dialog32": {
        "dialogText": "dialog 1 text",
        "choice": {
          "choice1Text": "Cloud City Bridge",
          "choice1Link": "Don't forget lightsaber",
          "choice2Text": "text",
          "choice2Link": "link",
          "choice3Text": "text",
          "choice3Link": "link"
        }
    },

  "dialog33": {
        "dialogText": "dialog 1 text",
        "choice": {
          "choice1Text": "Cloud City Bridge",
          "choice1Link": "Don't forget lightsaber",
          "choice2Text": "text",
          "choice2Link": "link",
          "choice3Text": "text",
          "choice3Link": "link"
    }
  }
}
